{
    "id": 4842,
    "house": "senate",
    "name": "Motions - Aquaculture Industry - Okehampton Bay salmon farm",
    "date": "2017-06-22",
    "number": 1,
    "clock_time": "12:24 PM",
    "aye_votes": 10,
    "no_votes": 40,
    "possible_turnout": 76,
    "rebellions": 0,
    "edited": true,
    "summary": "The majority voted against a [motion](https://www.openaustralia.org.au/senate/?id=2017-06-22.26.1) introduced by Greens Senator [Peter Whish-Wilson](https://theyvoteforyou.org.au/people/senate/tasmania/peter_whish-wilson) (Tas), which means it failed.\r\n\r\n### Motion text\r\n\r\n> *That the Senate—*\r\n\r\n> *(a) notes:*\r\n\r\n>> *(i) the damage caused to the Macquarie Harbour World Heritage Area, including the threat to the endangered Maugean Skate, as a result of the overstocking of salmon farms in the harbour,*\r\n\r\n>> *(ii) the proceedings brought by Huon Aquaculture in the Federal Court and the Tasmanian Supreme Court against the Tasmanian Government for failing to properly regulate salmon farming by Tassal in Macquarie Harbour,*\r\n\r\n>> *(iii) that the Commonwealth is investigating whether conditions imposed as part of the 2012 expansion of salmon farming in Macquarie Harbour have been breached,*\r\n\r\n>> *(iv) the decision of the Hodgman Government to grant permission to Tassal to establish an 800 000 fish salmon farm in Okehampton Bay on Tasmania's pristine east coast, and*\r\n\r\n>> *(v) concerns from a wide cross-section of the community over the proposed Okehampton Bay salmon farm, including the concerns expressed by around 1 000 people who attended FloatMo in Hobart on 18 June 2017; and*\r\n\r\n> *(b) calls on the Hodgman Government to withdraw permission for a salmon farm in Okehampton Bay given the record of atrocious mismanagement and poor regulation of Tasmania's aquaculture industry.*",
    "votes": [
        {
            "vote": "aye",
            "member": {
                "id": 100285,
                "person": {
                    "id": 10755
                },
                "first_name": "Richard",
                "last_name": "Di Natale",
                "electorate": "Victoria",
                "party": "Australian Greens"
            }
        },
        {
            "vote": "aye",
            "member": {
                "id": 100847,
                "person": {
                    "id": 10841
                },
                "first_name": "Nick",
                "last_name": "McKim",
                "electorate": "Tasmania",
                "party": "Australian Greens"
            }
        },
        {
            "vote": "aye",
            "member": {
                "id": 100258,
                "person": {
                    "id": 10713
                },
                "first_name": "Scott",
                "last_name": "Ludlam",
                "electorate": "WA",
                "party": "Australian Greens"
            }
        },
        {
            "vote": "aye",
            "member": {
                "id": 100256,
                "person": {
                    "id": 10711
                },
                "first_name": "Sarah",
                "last_name": "Hanson-Young",
                "electorate": "SA",
                "party": "Australian Greens"
            }
        },
        {
            "vote": "aye",
            "member": {
                "id": 100293,
                "person": {
                    "id": 10760
                },
                "first_name": "Lee",
                "last_name": "Rhiannon",
                "electorate": "NSW",
                "party": "Australian Greens"
            }
        },
        {
            "vote": "aye",
            "member": {
                "id": 100208,
                "person": {
                    "id": 10584
                },
                "first_name": "Rachel",
                "last_name": "Siewert",
                "electorate": "WA",
                "party": "Australian Greens"
            }
        },
        {
            "vote": "aye",
            "member": {
                "id": 100298,
                "person": {
                    "id": 10764
                },
                "first_name": "Larissa",
                "last_name": "Waters",
                "electorate": "Queensland",
                "party": "Australian Greens"
            }
        },
        {
            "vote": "aye",
            "member": {
                "id": 100842,
                "person": {
                    "id": 10830
                },
                "first_name": "Jacqui",
                "last_name": "Lambie",
                "electorate": "Tasmania",
                "party": "Independent"
            }
        },
        {
            "vote": "aye",
            "member": {
                "id": 100836,
                "person": {
                    "id": 10836
                },
                "first_name": "Janet",
                "last_name": "Rice",
                "electorate": "Victoria",
                "party": "Australian Greens"
            }
        },
        {
            "vote": "aye",
            "member": {
                "id": 100305,
                "person": {
                    "id": 10780
                },
                "first_name": "Peter",
                "last_name": "Whish-Wilson",
                "electorate": "Tasmania",
                "party": "Australian Greens"
            }
        },
        {
            "vote": "no",
            "member": {
                "id": 100844,
                "person": {
                    "id": 10838
                },
                "first_name": "Katy",
                "last_name": "Gallagher",
                "electorate": "ACT",
                "party": "Australian Labor Party"
            }
        },
        {
            "vote": "no",
            "member": {
                "id": 100835,
                "person": {
                    "id": 10835
                },
                "first_name": "Linda",
                "last_name": "Reynolds",
                "electorate": "WA",
                "party": "Liberal Party"
            }
        },
        {
            "vote": "no",
            "member": {
                "id": 100845,
                "person": {
                    "id": 10839
                },
                "first_name": "Jenny",
                "last_name": "McAllister",
                "electorate": "NSW",
                "party": "Australian Labor Party"
            }
        },
        {
            "vote": "no",
            "member": {
                "id": 100833,
                "person": {
                    "id": 10833
                },
                "first_name": "James",
                "last_name": "McGrath",
                "electorate": "Queensland",
                "party": "Liberal National Party"
            }
        },
        {
            "vote": "no",
            "member": {
                "id": 100849,
                "person": {
                    "id": 10845
                },
                "first_name": "James",
                "last_name": "Paterson",
                "electorate": "Victoria",
                "party": "Liberal Party"
            }
        },
        {
            "vote": "no",
            "member": {
                "id": 100871,
                "person": {
                    "id": 10419
                },
                "first_name": "Gavin",
                "last_name": "Marshall",
                "electorate": "Victoria",
                "party": "Australian Labor Party"
            }
        },
        {
            "vote": "no",
            "member": {
                "id": 100850,
                "person": {
                    "id": 10846
                },
                "first_name": "Patrick",
                "last_name": "Dodson",
                "electorate": "WA",
                "party": "Australian Labor Party"
            }
        },
        {
            "vote": "no",
            "member": {
                "id": 100868,
                "person": {
                    "id": 10898
                },
                "first_name": "Peter",
                "last_name": "Georgiou",
                "electorate": "WA",
                "party": "Pauline Hanson's One Nation Party"
            }
        },
        {
            "vote": "no",
            "member": {
                "id": 100866,
                "person": {
                    "id": 10038
                },
                "first_name": "Cory",
                "last_name": "Bernardi",
                "electorate": "SA",
                "party": "Australian Conservatives"
            }
        },
        {
            "vote": "no",
            "member": {
                "id": 100865,
                "person": {
                    "id": 10897
                },
                "first_name": "Kimberley",
                "last_name": "Kitching",
                "electorate": "Victoria",
                "party": "Australian Labor Party"
            }
        },
        {
            "vote": "no",
            "member": {
                "id": 100863,
                "person": {
                    "id": 10856
                },
                "first_name": "Malcolm",
                "last_name": "Roberts",
                "electorate": "Queensland",
                "party": "Pauline Hanson's One Nation Party"
            }
        },
        {
            "vote": "no",
            "member": {
                "id": 100861,
                "person": {
                    "id": 10855
                },
                "first_name": "Malarndirri",
                "last_name": "McCarthy",
                "electorate": "NT",
                "party": "Australian Labor Party"
            }
        },
        {
            "vote": "no",
            "member": {
                "id": 100859,
                "person": {
                    "id": 10853
                },
                "first_name": "Jane",
                "last_name": "Hume",
                "electorate": "Victoria",
                "party": "Liberal Party"
            }
        },
        {
            "vote": "no",
            "member": {
                "id": 100858,
                "person": {
                    "id": 10852
                },
                "first_name": "Derryn",
                "last_name": "Hinch",
                "electorate": "Victoria",
                "party": "Derryn Hinch's Justice Party"
            }
        },
        {
            "vote": "no",
            "member": {
                "id": 100857,
                "person": {
                    "id": 10280
                },
                "first_name": "Pauline",
                "last_name": "Hanson",
                "electorate": "Queensland",
                "party": "Pauline Hanson's One Nation Party"
            }
        },
        {
            "vote": "no",
            "member": {
                "id": 100855,
                "person": {
                    "id": 10708
                },
                "first_name": "Don",
                "last_name": "Farrell",
                "electorate": "SA",
                "party": "Australian Labor Party"
            }
        },
        {
            "vote": "no",
            "member": {
                "id": 100851,
                "person": {
                    "id": 10847
                },
                "first_name": "Jonathon",
                "last_name": "Duniam",
                "electorate": "Tasmania",
                "party": "Liberal Party"
            }
        },
        {
            "vote": "no",
            "member": {
                "id": 100832,
                "person": {
                    "id": 10832
                },
                "first_name": "David",
                "last_name": "Leyonhjelm",
                "electorate": "NSW",
                "party": "Liberal Democratic Party"
            }
        },
        {
            "vote": "no",
            "member": {
                "id": 100829,
                "person": {
                    "id": 10829
                },
                "first_name": "Chris",
                "last_name": "Ketter",
                "electorate": "Queensland",
                "party": "Australian Labor Party"
            }
        },
        {
            "vote": "no",
            "member": {
                "id": 100827,
                "person": {
                    "id": 10827
                },
                "first_name": "Matthew",
                "last_name": "Canavan",
                "electorate": "Queensland",
                "party": "Liberal National Party"
            }
        },
        {
            "vote": "no",
            "member": {
                "id": 100213,
                "person": {
                    "id": 10610
                },
                "first_name": "Glenn",
                "last_name": "Sterle",
                "electorate": "WA",
                "party": "Australian Labor Party"
            }
        },
        {
            "vote": "no",
            "member": {
                "id": 100199,
                "person": {
                    "id": 10569
                },
                "first_name": "Nigel",
                "last_name": "Scullion",
                "electorate": "NT",
                "party": "Country Liberal Party"
            }
        },
        {
            "vote": "no",
            "member": {
                "id": 100177,
                "person": {
                    "id": 10509
                },
                "first_name": "Marise",
                "last_name": "Payne",
                "electorate": "NSW",
                "party": "Liberal Party"
            }
        },
        {
            "vote": "no",
            "member": {
                "id": 100159,
                "person": {
                    "id": 10463
                },
                "first_name": "Claire",
                "last_name": "Moore",
                "electorate": "Queensland",
                "party": "Australian Labor Party"
            }
        },
        {
            "vote": "no",
            "member": {
                "id": 100130,
                "person": {
                    "id": 10401
                },
                "first_name": "Ian",
                "last_name": "Macdonald",
                "electorate": "Queensland",
                "party": "Liberal Party"
            }
        },
        {
            "vote": "no",
            "member": {
                "id": 100083,
                "person": {
                    "id": 10224
                },
                "first_name": "Mitch",
                "last_name": "Fifield",
                "electorate": "Victoria",
                "party": "Liberal Party"
            }
        },
        {
            "vote": "no",
            "member": {
                "id": 100082,
                "person": {
                    "id": 10222
                },
                "first_name": "Concetta",
                "last_name": "Fierravanti-Wells",
                "electorate": "NSW",
                "party": "Liberal Party"
            }
        },
        {
            "vote": "no",
            "member": {
                "id": 100031,
                "person": {
                    "id": 10085
                },
                "first_name": "David",
                "last_name": "Bushby",
                "electorate": "Tasmania",
                "party": "Liberal Party"
            }
        },
        {
            "vote": "no",
            "member": {
                "id": 100260,
                "person": {
                    "id": 10715
                },
                "first_name": "Scott",
                "last_name": "Ryan",
                "electorate": "Victoria",
                "party": "Liberal Party"
            }
        },
        {
            "vote": "no",
            "member": {
                "id": 100261,
                "person": {
                    "id": 10716
                },
                "first_name": "John",
                "last_name": "Williams",
                "electorate": "NSW",
                "party": "National Party"
            }
        },
        {
            "vote": "no",
            "member": {
                "id": 100279,
                "person": {
                    "id": 10722
                },
                "first_name": "Christopher",
                "last_name": "Back",
                "electorate": "WA",
                "party": "Liberal Party"
            }
        },
        {
            "vote": "no",
            "member": {
                "id": 100313,
                "person": {
                    "id": 10824
                },
                "first_name": "Barry",
                "last_name": "O'Sullivan",
                "electorate": "Queensland",
                "party": "National Party"
            }
        },
        {
            "vote": "no",
            "member": {
                "id": 100306,
                "person": {
                    "id": 10781
                },
                "first_name": "Anne",
                "last_name": "Ruston",
                "electorate": "SA",
                "party": "Liberal Party"
            }
        },
        {
            "vote": "no",
            "member": {
                "id": 100303,
                "person": {
                    "id": 10768
                },
                "first_name": "Dean",
                "last_name": "Smith",
                "electorate": "WA",
                "party": "Liberal Party"
            }
        },
        {
            "vote": "no",
            "member": {
                "id": 100301,
                "person": {
                    "id": 10766
                },
                "first_name": "Arthur",
                "last_name": "Sinodinos",
                "electorate": "NSW",
                "party": "Liberal Party"
            }
        },
        {
            "vote": "no",
            "member": {
                "id": 100297,
                "person": {
                    "id": 10763
                },
                "first_name": "Anne",
                "last_name": "Urquhart",
                "electorate": "Tasmania",
                "party": "Australian Labor Party"
            }
        },
        {
            "vote": "no",
            "member": {
                "id": 100291,
                "person": {
                    "id": 10758
                },
                "first_name": "Bridget",
                "last_name": "McKenzie",
                "electorate": "Victoria",
                "party": "National Party"
            }
        },
        {
            "vote": "no",
            "member": {
                "id": 100288,
                "person": {
                    "id": 10757
                },
                "first_name": "Alex",
                "last_name": "Gallacher",
                "electorate": "SA",
                "party": "Australian Labor Party"
            }
        },
        {
            "vote": "no",
            "member": {
                "id": 100287,
                "person": {
                    "id": 10215
                },
                "first_name": "David",
                "last_name": "Fawcett",
                "electorate": "SA",
                "party": "Liberal Party"
            }
        },
        {
            "vote": "no",
            "member": {
                "id": 100026,
                "person": {
                    "id": 10071
                },
                "first_name": "Carol",
                "last_name": "Brown",
                "electorate": "Tasmania",
                "party": "Australian Labor Party"
            }
        }
    ],
    "policy_divisions": [
        {
            "policy": {
                "id": 17,
                "name": "increasing marine conservation",
                "description": "the federal government should introduce legislation and regulations that protect and conserve Australia's marine ecosystems such as the Great Barrier Reef",
                "provisional": false
            },
            "vote": "aye",
            "strong": false
        },
        {
            "policy": {
                "id": 41,
                "name": "increasing fishing restrictions",
                "description": "the federal government should increase fishing restrictions so that fish populations are sustainable",
                "provisional": false
            },
            "vote": "aye",
            "strong": false
        }
    ],
    "bills": []
}